spellingbee.py
spelling_bee_tts-0.4.2.data/data/share/applications/spelling-bee-tts.desktop
spelling_bee_tts-0.4.2.data/data/share/icons/hicolor/256x256/apps/spelling-bee-tts.png
spelling_bee_tts-0.4.2.data/data/share/spellingbee/words.csv.gz
spelling_bee_tts-0.4.2.dist-info/licenses/LICENSE
spelling_bee_tts-0.4.2.dist-info/METADATA
spelling_bee_tts-0.4.2.dist-info/WHEEL
spelling_bee_tts-0.4.2.dist-info/entry_points.txt
spelling_bee_tts-0.4.2.dist-info/top_level.txt
spelling_bee_tts-0.4.2.dist-info/RECORD
