Metadata-Version: 2.4
Name: spelling-bee-tts
Version: 0.4.2
Summary: GTK4 spelling quiz app with text-to-speech and AI generated example sentences.
Requires-Python: >=3.9
License-File: LICENSE
Requires-Dist: edge-tts>=7.2.7
Requires-Dist: huggingface_hub>=0.24.6
Requires-Dist: llama-cpp-python>=0.2.90
Dynamic: license-file
